{
  "layouts": {
    "keymap": [
      [
        {
          "w": 2,
          "h": 2
        },
        "2,3",
        {
          "x": 0.25
        },
        "0,2",
        "0,3"
      ],
      [
        {
          "x": 2.25
        },
        "1,2",
        "1,3"
      ],
      [
        {
          "y": 0.25
        },
        "2,0",
        "2,1",
        "2,2",
        {
          "x": 0.25,
          "h": 2
        },
        "3,3"
      ],
      [
        "3,0",
        "3,1",
        "3,2"
      ],
      [
        "4,0",
        "4,1",
        "4,2",
        {
          "x": 0.25
        },
        "4,3"
      ],
      [
        "5,0",
        "5,1",
        "5,2",
        {
          "x": 0.25
        },
        "5,3"
      ]
    ]
  },
  "name": "sinpad20",
  "vendorId": "0xCEE9",
  "productId": "0x0001",
  "lighting": "none",
  "matrix": {
    "rows": 6,
    "cols": 4
  }
}